README.rst
setup.cfg
setup.py
src/codeviking.astro.units.egg-info/PKG-INFO
src/codeviking.astro.units.egg-info/SOURCES.txt
src/codeviking.astro.units.egg-info/dependency_links.txt
src/codeviking.astro.units.egg-info/not-zip-safe
src/codeviking.astro.units.egg-info/top_level.txt
src/codeviking/astro/units/__init__.py
src/codeviking/astro/units/_version.py
test/test_distance.py
test/test_mass.py
test/test_time.py